promptsec
